{"resources":{"wood":100,"food":9,"gold":50,"stone":200},"villagers":{"wood":7,"food":12,"gold":0,"stone":0,"total":19,"idle":0},"population":{"current":20,"maximum":20},"age":{"numeral":"I","text":"Feudal Age"},"metadata":{"home":"Hera","away":"Opponents","desc":"Ranked","metadate":"10 April 2025","wins":7,"losses":1},"gametime":{"hours":0,"minutes":7,"seconds":11},"top_player":{"number":1,"name":"GL.Hera","score_individual":761,"score_team":761,"age_numeral":"I"},"bottom_player":{"number":2,"name":"TAG_MbL_","score_individual":711,"score_team":711,"age_numeral":"I"},"selected_info":{"player_name":null,"civilization":null}}