{"resources":{"wood":612,"food":541,"gold":89,"stone":783},"villagers":{"wood":26,"food":42,"gold":21,"stone":9,"total":102,"idle":3},"population":{"current":117,"maximum":125},"age":{"numeral":"III","text":"Imperial Age"},"metadata":{"home":"Hera","away":"Opponents","desc":"Ranked","metadate":"14 April 2025","wins":1,"losses":0},"gametime":{"hours":0,"minutes":32,"seconds":57},"top_player":{"number":1,"name":"GL.Hera","score_individual":4939,"score_team":4939,"age_numeral":"III"},"bottom_player":{"number":2,"name":"弄双提影","score_individual":4861,"score_team":4861,"age_numeral":"III"},"selected_info":{"player_name":"GL.Hera","civilization":"Franks"}}