{"frame2data":{"28684":{"resources":{"wood":106,"food":8,"gold":69,"stone":200},"villagers":{"wood":10,"food":15,"gold":2,"stone":0,"total":27,"idle":0},"population":{"current":30,"maximum":40},"age":{"numeral":"I","text":"Feudal Age"},"metadata":{"home":"Hera","away":"Opponents","desc":"Ranked","metadate":"27 Feb 2025","wins":6,"losses":2},"gametime":{"hours":0,"minutes":12,"seconds":52},"top_player":{"number":1,"name":"GL.Hera","score_individual":1014,"score_team":1014,"age_numeral":"I"},"bottom_player":{"number":2,"name":"_LY_ 耸耷肥龙","score_individual":1007,"score_team":1007,"age_numeral":"II"},"selected_info":{"player_name":null,"civilization":null}},"53959":{"resources":{"wood":251,"food":4,"gold":84,"stone":200},"villagers":{"wood":17,"food":19,"gold":7,"stone":0,"total":43,"idle":0},"population":{"current":68,"maximum":85},"age":{"numeral":"II","text":"Castle Age"},"metadata":{"home":"Hera","away":"Opponents","desc":"Ranked","metadate":"27 Feb 2025","wins":6,"losses":2},"gametime":{"hours":0,"minutes":24,"seconds":17},"top_player":{"number":2,"name":"_LY","score_individual":2400,"score_team":2400,"age_numeral":"III"},"bottom_player":{"number":1,"name":"GL.Hera","score_individual":2345,"score_team":2345,"age_numeral":"II"},"selected_info":{"player_name":null,"civilization":null}},"96462":{"resources":{"wood":null,"food":null,"gold":null,"stone":null},"villagers":{"wood":null,"food":null,"gold":null,"stone":null,"total":null,"idle":null},"population":{"current":null,"maximum":null},"age":{"numeral":null,"text":null},"metadata":{"home":null,"away":null,"desc":null,"metadate":null,"wins":null,"losses":null},"gametime":{"hours":null,"minutes":null,"seconds":null},"top_player":{"number":null,"name":null,"score_individual":null,"score_team":null,"age_numeral":null},"bottom_player":{"number":null,"name":null,"score_individual":null,"score_team":null,"age_numeral":null},"selected_info":{"player_name":null,"civilization":null}},"145":{"resources":{"wood":200,"food":200,"gold":100,"stone":200},"villagers":{"wood":0,"food":null,"gold":0,"stone":1,"total":3,"idle":null},"population":{"current":4,"maximum":5},"age":{"numeral":"I","text":"Dark Age"},"metadata":{"home":"Hera","away":"Opponents","desc":"Ranked","metadate":"27 Feb 2025","wins":6,"losses":2},"gametime":{"hours":0,"minutes":40,"seconds":0},"top_player":{"number":null,"name":"GL.Hera","score_individual":null,"score_team":null,"age_numeral":"II"},"bottom_player":{"number":null,"name":"LN","score_individual":null,"score_team":null,"age_numeral":null},"selected_info":{"player_name":null,"civilization":null}},"33436":{"resources":{"wood":456,"food":376,"gold":149,"stone":200},"villagers":{"wood":10,"food":7,"gold":2,"stone":0,"total":27,"idle":0},"population":{"current":28,"maximum":35},"age":{"numeral":"II","text":"Feudal Age"},"metadata":{"home":"Hera","away":"Opponents","desc":"Ranked","metadate":"27 Feb 2025","wins":6,"losses":2},"gametime":{"hours":0,"minutes":15,"seconds":1},"top_player":{"number":2,"name":"_LY_ 斗智肥应","score_individual":1404,"score_team":1404,"age_numeral":"II"},"bottom_player":{"number":1,"name":"GL.Hera","score_individual":1102,"score_team":1102,"age_numeral":"I"},"selected_info":{"player_name":null,"civilization":null}},"59807":{"resources":{"wood":282,"food":297,"gold":135,"stone":200},"villagers":{"wood":12,"food":17,"gold":10,"stone":0,"total":41,"idle":1},"population":{"current":67,"maximum":100},"age":{"numeral":"III","text":"Castle Age"},"metadata":{"home":"Hera","away":"Opponents","desc":"Ranked","metadate":"27 Feb 2025","wins":6,"losses":2},"gametime":{"hours":0,"minutes":26,"seconds":55},"top_player":{"number":2,"name":"_LY","score_individual":2799,"score_team":2799,"age_numeral":"III"},"bottom_player":{"number":1,"name":"GL.Hera","score_individual":2587,"score_team":2587,"age_numeral":"II"},"selected_info":{"player_name":null,"civilization":null}},"95239":{"resources":{"wood":275,"food":527,"gold":835,"stone":550},"villagers":{"wood":null,"food":25,"gold":24,"stone":16,"total":82,"idle":6},"population":{"current":138,"maximum":195},"age":{"numeral":"III","text":"Castle Age"},"metadata":{"home":"Hera","away":"Opponents","desc":"Ranked","metadate":"27 Feb 2025","wins":6,"losses":2},"gametime":{"hours":0,"minutes":41,"seconds":44},"top_player":{"number":null,"name":"GL.Hera","score_individual":null,"score_team":null,"age_numeral":"III"},"bottom_player":{"number":null,"name":null,"score_individual":null,"score_team":null,"age_numeral":null},"selected_info":{"player_name":null,"civilization":null}}}}