{"resources":{"wood":454,"food":164,"gold":48,"stone":929},"villagers":{"wood":33,"food":49,"gold":19,"stone":8,"total":117,"idle":2},"population":{"current":150,"maximum":155},"age":{"numeral":"III","text":"Imperial Age"},"metadata":{"home":"Hera","away":"Opponents","desc":"7 Games","metadate":"16 April 2025","wins":1,"losses":0},"gametime":{"hours":0,"minutes":36,"seconds":24},"top_player":{"number":1,"name":"GL.Hera","score_individual":77,"score_team":77,"age_numeral":"III"},"bottom_player":{"number":7,"name":"TAG_MbL_","score_individual":521,"score_team":521,"age_numeral":"IV"},"selected_info":{"player_name":"GL.Hera","civilization":"Burgundians"}}