{"frame2data":{"48972":"Feudal Age","24486":"Dark Age","36729":"Feudal Age","30608":"Dark Age","33669":"Feudal Age","32139":"Dark Age","32904":"Feudal Age","32522":"Feudal Age","32331":"Feudal Age","32235":"Dark Age","32283":"Dark Age","32307":"Feudal Age","32295":"Feudal Age","32289":"Dark Age","32292":"Dark Age","32294":"Feudal Age","32293":"Dark Age","73459":"Castle Age","61216":"Castle Age","55094":"Castle Age","52033":"Castle Age","50503":"Castle Age","49738":"Castle Age","49355":"Feudal Age","49547":"Feudal Age","49643":"Feudal Age","49691":"Feudal Age","49715":"Feudal Age","49727":"Feudal Age","49733":"Castle Age","49730":"Feudal Age","49732":"Castle Age","49731":"Feudal Age","85702":"Imperial Age","79581":"Imperial Age","76520":"Imperial Age","74990":"Imperial Age","74225":"Castle Age","74608":"Castle Age","74799":"Imperial Age","74704":"Imperial Age","74656":"Imperial Age","74632":"Imperial Age","74620":"Imperial Age","74614":"Castle Age","74617":"Castle Age","74619":"Imperial Age","74618":"Imperial Age","73458":"Castle Age","85701":"Imperial Age","91823":"Imperial Age","94884":"Imperial Age","96414":"Imperial Age","97179":null,"96796":"Imperial Age","96987":"Imperial Age","97082":null,"97034":null,"97010":"Imperial Age","97021":null,"97015":null,"97012":"Feudal Age","97013":"Feudal Age","97014":null}}